config/__init__.py
mongodb_ml_models/__init__.py
mongodb_ml_models/constants.py
mongodb_ml_models/directory_handling.py
mongodb_ml_models/mongodb_handle.py
mongodb_ml_models/mongodb_models_handle.py
mongodb_ml_models-1.0.0.dist-info/LICENSE
mongodb_ml_models-1.0.0.dist-info/METADATA
mongodb_ml_models-1.0.0.dist-info/WHEEL
mongodb_ml_models-1.0.0.dist-info/top_level.txt
mongodb_ml_models-1.0.0.dist-info/RECORD
