Metadata-Version: 2.1
Name: mongodb-ml-models
Version: 1.0.0
Summary: For handling binary machine learning models in mongodb
Home-page: https://github.com/jassim-jasmin/mongodb_model
Author: Mohammed Jassim
Author-email: mohammedjassim.jasmir@gmail.com
License: UNKNOWN
Project-URL: Bug Tracker, https://github.com/pypa/sampleproject/issues
Keywords: pymongo pymongo-ml-model ml-model
Platform: UNKNOWN
Classifier: Programming Language :: Python :: 3.8
Classifier: License :: OSI Approved :: MIT License
Classifier: Operating System :: OS Independent
Requires-Python: >=3.8
License-File: LICENSE
Requires-Dist: pymongo
Requires-Dist: python-decouple
Requires-Dist: joblib
